ddg_scraper/__init__.py
ddg_scraper/core.py
ddg_scraper/http.py
ddg_scraper/parser.py
ddg_scraper/scraper.py
ddg_scraper/structs.py
ddg_scraper/abc/__init__.py
ddg_scraper/abc/coroutine_handler.py
ddg_scraper-2.0.1.dist-info/LICENSE
ddg_scraper-2.0.1.dist-info/METADATA
ddg_scraper-2.0.1.dist-info/WHEEL
ddg_scraper-2.0.1.dist-info/top_level.txt
ddg_scraper-2.0.1.dist-info/RECORD
